qwed_tax/__init__.py
qwed_tax/address_guard.py
qwed_tax/models.py
qwed_tax/verifier.py
qwed_tax/guards/classification_guard.py
qwed_tax/guards/nexus_guard.py
qwed_tax/jurisdictions/india/__init__.py
qwed_tax/jurisdictions/india/guards/crypto_guard.py
qwed_tax/jurisdictions/india/guards/deposit_guard.py
qwed_tax/jurisdictions/india/guards/gst_guard.py
qwed_tax/jurisdictions/india/guards/investment_guard.py
qwed_tax/jurisdictions/india/guards/setoff_guard.py
qwed_tax/jurisdictions/us/classification_guard.py
qwed_tax/jurisdictions/us/form1099_guard.py
qwed_tax/jurisdictions/us/payroll_guard.py
qwed_tax/jurisdictions/us/reciprocity_guard.py
qwed_tax/jurisdictions/us/withholding_guard.py
qwed_tax-0.1.0.dist-info/METADATA
qwed_tax-0.1.0.dist-info/WHEEL
qwed_tax-0.1.0.dist-info/licenses/LICENSE
qwed_tax-0.1.0.dist-info/RECORD
