Metadata-Version: 2.4
Name: qwed-tax
Version: 0.1.0
Summary: Deterministic Verification for Payroll and Tax Compliance.
Author-email: QWED Team <rahul@qwedai.com>
License: Apache-2.0
License-File: LICENSE
Requires-Python: >=3.10
Requires-Dist: colorama>=0.4.6
Requires-Dist: pydantic>=2.0.0
Requires-Dist: z3-solver>=4.12.0
Provides-Extra: dev
Requires-Dist: black>=23.0.0; extra == 'dev'
Requires-Dist: pytest-cov>=4.1.0; extra == 'dev'
Requires-Dist: pytest>=7.0.0; extra == 'dev'
